tacp/__init__.py
tacp/api_client.py
tacp/configuration.py
tacp/rest.py
tacp/api/__init__.py
tacp/api/actions_api.py
tacp/api/application_groups_api.py
tacp/api/applications_api.py
tacp/api/categories_api.py
tacp/api/compute_nodes_api.py
tacp/api/datacenters_api.py
tacp/api/defaults_api.py
tacp/api/edit_applications_api.py
tacp/api/events_api.py
tacp/api/firewall_profiles_api.py
tacp/api/flash_pools_api.py
tacp/api/locations_api.py
tacp/api/marketplace_templates_api.py
tacp/api/migration_zones_api.py
tacp/api/storage_blocks_api.py
tacp/api/storage_controllers_api.py
tacp/api/tags_api.py
tacp/api/templates_api.py
tacp/api/users_api.py
tacp/api/version_api.py
tacp/api/vlans_api.py
tacp/api/vnets_api.py
tacp/models/__init__.py
tacp/models/api_action_payload.py
tacp/models/api_action_status_payload.py
tacp/models/api_add_vnic_payload.py
tacp/models/api_application_group_payload.py
tacp/models/api_application_instance_properties_payload.py
tacp/models/api_application_instance_stats_payload.py
tacp/models/api_application_template_operating_system_payload.py
tacp/models/api_application_template_properties_payload.py
tacp/models/api_applications_for_application_group_payload.py
tacp/models/api_automated_snapshot_policy_payload.py
tacp/models/api_boot_order_payload.py
tacp/models/api_category_allocation_for_migration_zone_payload.py
tacp/models/api_category_allocation_payload.py
tacp/models/api_compute_hardware_properties_payload.py
tacp/models/api_compute_node_firmware_update_payload.py
tacp/models/api_compute_node_stats_payload.py
tacp/models/api_controller_status_payload.py
tacp/models/api_cpu_temperature_payload.py
tacp/models/api_create_application_group_payload.py
tacp/models/api_create_application_payload.py
tacp/models/api_create_datacenter_category_allocation_payload.py
tacp/models/api_create_datacenter_payload.py
tacp/models/api_create_datacenter_resource_payload.py
tacp/models/api_create_or_edit_application_network_options_payload.py
tacp-5.1.3.1.dist-info/LICENSE
tacp-5.1.3.1.dist-info/METADATA
tacp-5.1.3.1.dist-info/WHEEL
tacp-5.1.3.1.dist-info/top_level.txt
tacp-5.1.3.1.dist-info/RECORD
