Metadata-Version: 2.1
Name: tacp
Version: 5.1.3.1
Summary: CP Web Services (CPWS)
Home-page: UNKNOWN
Author: UNKNOWN
Author-email: amadsen@lenovo.com
License: UNKNOWN
Keywords: Swagger,CP Web Services (CPWS)
Platform: UNKNOWN
Requires-Dist: urllib3 (>=1.15)
Requires-Dist: six (>=1.10)
Requires-Dist: certifi
Requires-Dist: python-dateutil
